maskrcnn_modanet/__init__.py
maskrcnn_modanet/arrange_annotations.py
maskrcnn_modanet/arrange_images.py
maskrcnn_modanet/download.sh
maskrcnn_modanet/evaluatemodel.py
maskrcnn_modanet/fix_annotations.py
maskrcnn_modanet/instagram_impl.py
maskrcnn_modanet/processimages.py
maskrcnn_modanet/viewannotations.py
maskrcnn_modanet/viewimages.py
maskrcnn_modanet/viewimagescoco.py
maskrcnn_modanet/cli/__init__.py
maskrcnn_modanet/cli/main.py
maskrcnn_modanet/cli/validators.py
maskrcnn_modanet/train/__init__.py
maskrcnn_modanet/train/coco.py
maskrcnn_modanet/train/generator.py
maskrcnn_modanet/train/train.py
maskrcnn_modanet-1.0.3.dist-info/LICENSE
maskrcnn_modanet-1.0.3.dist-info/METADATA
maskrcnn_modanet-1.0.3.dist-info/WHEEL
maskrcnn_modanet-1.0.3.dist-info/entry_points.txt
maskrcnn_modanet-1.0.3.dist-info/top_level.txt
maskrcnn_modanet-1.0.3.dist-info/RECORD
