Metadata-Version: 2.1
Name: maskrcnn-modanet
Version: 1.0.3
Summary: A MaskRCNN Keras implementation with Modanet annotations on the Paperdoll dataset
Home-page: https://github.com/cad0p/maskrcnn-modanet
Author: Pier Carlo Cadoppi
Author-email: piercarlo.cadoppi@studenti.unipr.it
License: UNKNOWN
Platform: UNKNOWN
Classifier: Programming Language :: Python :: 3
Classifier: License :: OSI Approved :: MIT License
Classifier: Operating System :: OS Independent
Requires-Dist: keras-maskrcnn
Requires-Dist: click
Requires-Dist: progressbar
Requires-Dist: lmdb
Requires-Dist: pandas
Requires-Dist: sqlalchemy
Requires-Dist: Cython
Requires-Dist: cython
Requires-Dist: numpy
Requires-Dist: pycocotools
Requires-Dist: matplotlib
Requires-Dist: tensorflow
Requires-Dist: instaloader
